translator/__init__.py
translator/glossary.py
translator/translate_generator.py
translator/utils.py
translator_json-1.0.9.dist-info/METADATA
translator_json-1.0.9.dist-info/WHEEL
translator_json-1.0.9.dist-info/entry_points.txt
translator_json-1.0.9.dist-info/top_level.txt
translator_json-1.0.9.dist-info/RECORD
