Metadata-Version: 2.1
Name: translator-json
Version: 1.0.9
Summary: A translator for Json info
Author-email: Florent Simonnot <contact@gwanly.com>
License: Apache Software License
Project-URL: Repository, https://gitlab.com/FlorentSimonnot1/translator
Classifier: Programming Language :: Python :: 3.8
Classifier: Operating System :: OS Independent
Classifier: License :: OSI Approved :: Apache Software License
Requires-Python: >=3.8
Requires-Dist: wheel (>=0.37.0)
Requires-Dist: twine (~=3.4.1)
Requires-Dist: click (==8.0.3)
Requires-Dist: pycodestyle (>=2.7.0)
Requires-Dist: google-cloud-translate (==3.11.1)
Requires-Dist: setuptools (~=60.2.0)
Requires-Dist: build
